klongpy/__init__.py
klongpy/adverbs.py
klongpy/backend.py
klongpy/core.py
klongpy/dyads.py
klongpy/interpreter.py
klongpy/monads.py
klongpy/repl.py
klongpy/sys_fn.py
klongpy/sys_fn_ipc.py
klongpy/sys_fn_timer.py
klongpy/sys_var.py
klongpy/utils.py
klongpy/db/__init__.py
klongpy/db/df_cache.py
klongpy/db/file_cache.py
klongpy/db/helpers.py
klongpy/db/sys_fn_db.py
klongpy/db/sys_fn_kvs.py
klongpy/lib/csv.kg
klongpy/lib/edt.kg
klongpy/lib/eigenv.kg
klongpy/lib/help.kg
klongpy/lib/huffman.kg
klongpy/lib/math.kg
klongpy/lib/nstat.kg
klongpy/lib/print.kg
klongpy/lib/set.kg
klongpy/lib/spline.kg
klongpy/lib/time.kg
klongpy/lib/util.kg
klongpy/web/__init__.py
klongpy/web/sys_fn_web.py
klongpy/ws/__init__.py
klongpy/ws/sys_fn_ws.py
klongpy-0.6.9.data/scripts/kgpy
klongpy-0.6.9.dist-info/licenses/LICENSE
tests/__init__.py
tests/gen_join_over.py
tests/gen_py_suite.py
tests/gen_test_fn.py
tests/perf_async.py
tests/perf_avg.py
tests/perf_duckdb.py
tests/perf_gen.py
tests/perf_ipc_overhead.py
tests/perf_join.py
tests/perf_load.py
tests/perf_prog.py
tests/perf_serdes.py
tests/perf_sys_fn_db.py
tests/perf_vector.py
tests/test_accel.py
tests/test_df_cache.py
tests/test_eval_monad_list.py
tests/test_examples.py
tests/test_extra_suite.py
tests/test_file_cache.py
tests/test_interop.py
tests/test_kg_asarray.py
tests/test_kgtests.py
tests/test_known_bugs.py
tests/test_prog.py
tests/test_reshape_strings.py
tests/test_suite.py
tests/test_suite_file.py
tests/test_sys_fn.py
tests/test_sys_fn_db.py
tests/test_sys_fn_ipc.py
tests/test_sys_fn_timer.py
tests/test_sys_fn_web.py
tests/test_util.py
tests/utils.py
klongpy-0.6.9.dist-info/METADATA
klongpy-0.6.9.dist-info/WHEEL
klongpy-0.6.9.dist-info/top_level.txt
klongpy-0.6.9.dist-info/RECORD
