Metadata-Version: 2.4
Name: klongpy
Version: 0.6.9
Summary: High-Performance Klong array language with rich Python integration.
Author: Brian Guarraci
License: MIT
Classifier: Programming Language :: Python :: 3
Classifier: License :: OSI Approved :: MIT License
Requires-Python: <3.13,>=3.9
License-File: LICENSE
Requires-Dist: numpy~=1.26.4
Provides-Extra: cupy
Requires-Dist: cupy; extra == "cupy"
Provides-Extra: cuda12x
Requires-Dist: cupy-cuda12x; extra == "cuda12x"
Provides-Extra: cuda11x
Requires-Dist: cupy-cuda11x; extra == "cuda11x"
Provides-Extra: cuda111
Requires-Dist: cupy-cuda111; extra == "cuda111"
Provides-Extra: cuda110
Requires-Dist: cupy-cuda110; extra == "cuda110"
Provides-Extra: cuda102
Requires-Dist: cupy-cuda102; extra == "cuda102"
Provides-Extra: rocm-5-0
Requires-Dist: cupy-rocm-5-0; extra == "rocm-5-0"
Provides-Extra: rocm-4-3
Requires-Dist: cupy-rocm-4-3; extra == "rocm-4-3"
Provides-Extra: repl
Requires-Dist: colorama==0.4.6; extra == "repl"
Provides-Extra: web
Requires-Dist: aiohttp==3.9.4; extra == "web"
Provides-Extra: db
Requires-Dist: pandas==2.2.2; extra == "db"
Requires-Dist: duckdb==1.3.0; extra == "db"
Provides-Extra: ws
Requires-Dist: websockets==12.0; extra == "ws"
Provides-Extra: full
Requires-Dist: colorama==0.4.6; extra == "full"
Requires-Dist: aiohttp==3.9.4; extra == "full"
Requires-Dist: pandas==2.2.2; extra == "full"
Requires-Dist: duckdb==1.3.0; extra == "full"
Requires-Dist: websockets==12.0; extra == "full"
Dynamic: author
Dynamic: classifier
Dynamic: description
Dynamic: description-content-type
Dynamic: license
Dynamic: license-file
Dynamic: provides-extra
Dynamic: requires-dist
Dynamic: requires-python
Dynamic: summary
